pyminufit/__init__.py
pyminufit/_version.pyi
pyminufit/composites.py
pyminufit/models.py
pyminufit/observables.py
pyminufit/pdf.py
pyminufit/plotting.py
pyminufit/py.typed
pyminufit/utils.py
pyminufit/version.py
pyminufit-0.2.2.dist-info/METADATA
pyminufit-0.2.2.dist-info/WHEEL
pyminufit-0.2.2.dist-info/licenses/LICENSE
pyminufit-0.2.2.dist-info/RECORD
